doc_quality/__init__.py
doc_quality/metrics.py
doc_quality/suggestions.py
doc_quality/utils.py
doc_quality-0.1.0.dist-info/METADATA
doc_quality-0.1.0.dist-info/WHEEL
doc_quality-0.1.0.dist-info/top_level.txt
doc_quality-0.1.0.dist-info/RECORD
